README.rst
setup.py
django_kaneda/__init__.py
django_kaneda/settings.py
kaneda/__init__.py
kaneda/base.py
kaneda/exceptions.py
kaneda/utils.py
kaneda.egg-info/PKG-INFO
kaneda.egg-info/SOURCES.txt
kaneda.egg-info/dependency_links.txt
kaneda.egg-info/entry_points.txt
kaneda.egg-info/requires.txt
kaneda.egg-info/top_level.txt
kaneda/backends/__init__.py
kaneda/backends/base.py
kaneda/backends/elasticsearch.py
kaneda/backends/influxdb.py
kaneda/backends/logger.py
kaneda/backends/mongodb.py
kaneda/backends/rethink.py
kaneda/queues/__init__.py
kaneda/queues/base.py
kaneda/queues/celery.py
kaneda/queues/rq.py
kaneda/queues/zmq.py
kaneda/tasks/__init__.py
kaneda/tasks/celery.py
kaneda/tasks/rq.py
kaneda/tasks/zmq.py
tests/__init__.py
tests/conftest.py
tests/integration/__init__.py
tests/integration/conftest.py
tests/integration/test_backends.py
tests/integration/test_metrics.py
tests/integration/test_queues.py
tests/integration/benchmarks/__init__.py
tests/integration/benchmarks/test_backends.py
tests/integration/benchmarks/test_queues.py
tests/integration/django/__init__.py
tests/integration/django/conftest.py
tests/integration/django/test_django.py
tests/unit/__init__.py
tests/unit/conftest.py
tests/unit/test_backends.py
tests/unit/test_metrics.py
tests/unit/test_utils.py