Metadata-Version: 1.1
Name: kaneda
Version: 0.5
Summary: Configurable Python library for metrics and events reporting
Home-page: UNKNOWN
Author: Marc Tudurí
Author-email: mtuduri@apsl.net
License: UNKNOWN
Platform: UNKNOWN
Classifier: Intended Audience :: Developers
Classifier: Programming Language :: Python
Classifier: Programming Language :: Python :: 2
Classifier: Programming Language :: Python :: 2.7
Classifier: Programming Language :: Python :: 3
Classifier: Programming Language :: Python :: 3.3
Classifier: Programming Language :: Python :: 3.4
Classifier: Operating System :: OS Independent
Classifier: Topic :: Software Development
